odoo/addons/datetime_formatter/README.rst
odoo/addons/datetime_formatter/__init__.py
odoo/addons/datetime_formatter/__manifest__.py
odoo/addons/datetime_formatter/i18n/ar.po
odoo/addons/datetime_formatter/i18n/ca.po
odoo/addons/datetime_formatter/i18n/de.po
odoo/addons/datetime_formatter/i18n/es.po
odoo/addons/datetime_formatter/i18n/fr.po
odoo/addons/datetime_formatter/i18n/hr.po
odoo/addons/datetime_formatter/i18n/it.po
odoo/addons/datetime_formatter/i18n/nl_NL.po
odoo/addons/datetime_formatter/i18n/sl.po
odoo/addons/datetime_formatter/i18n/tr.po
odoo/addons/datetime_formatter/models/__init__.py
odoo/addons/datetime_formatter/models/res_lang.py
odoo/addons/datetime_formatter/static/description/icon.png
odoo/addons/datetime_formatter/tests/__init__.py
odoo/addons/datetime_formatter/tests/test_best_matcher.py
odoo/addons/datetime_formatter/tests/test_formatter.py
odoo11_addon_datetime_formatter-11.0.1.0.0.dist-info/DESCRIPTION.rst
odoo11_addon_datetime_formatter-11.0.1.0.0.dist-info/METADATA
odoo11_addon_datetime_formatter-11.0.1.0.0.dist-info/RECORD
odoo11_addon_datetime_formatter-11.0.1.0.0.dist-info/WHEEL
odoo11_addon_datetime_formatter-11.0.1.0.0.dist-info/metadata.json
odoo11_addon_datetime_formatter-11.0.1.0.0.dist-info/top_level.txt
