Metadata-Version: 2.0
Name: odoo11-addon-datetime-formatter
Version: 11.0.1.0.0
Summary: Helper functions to give correct format to date[time] fields
Home-page: https://www.tecnativa.com
Author: Grupo ESOC Ingeniería de Servicios, Tecnativa,Odoo Community Association (OCA)
Author-email: support@odoo-community.org
License: AGPL-3
Platform: UNKNOWN
Classifier: Programming Language :: Python
Classifier: Framework :: Odoo
Classifier: License :: OSI Approved :: GNU Affero General Public License v3
Requires-Python: >=2.7, !=3.0.*, !=3.1.*, !=3.2.*, !=3.3.*, !=3.4.*
Requires-Dist: odoo (<11.1dev,>=11.0a)
